{
  "groups": [
    {
      "name": "sys.security",
      "type": "com.sys.security.core.properties.SysSecurityProperties",
      "sourceType": "com.sys.security.core.properties.SysSecurityProperties"
    }
  ],
  "properties": [
    {
      "name": "sys.security.browser",
      "type": "com.sys.security.core.properties.BrowserProperties",
      "sourceType": "com.sys.security.core.properties.SysSecurityProperties"
    },
    {
      "name": "sys.security.code",
      "type": "com.sys.security.core.properties.ValidateCodeProperties",
      "sourceType": "com.sys.security.core.properties.SysSecurityProperties"
    },
    {
      "name": "sys.security.social",
      "type": "com.sys.security.core.properties.SocialProperties",
      "sourceType": "com.sys.security.core.properties.SysSecurityProperties"
    }
  ],
  "hints": []
}